Metadata-Version: 1.1
Name: ascii-image
Version: 1.2
Summary: Make any image file to ascii art format.
Home-page: https://github.com/Henry0526/ascii_image
Author: Hao-Wei Li
Author-email: henryliking@gmail.com
License: MIT
Keywords: ASCII-art,image,ascii
Platform: UNKNOWN
Classifier: Development Status :: 5 - Production/Stable
Classifier: License :: OSI Approved :: MIT License
Classifier: Programming Language :: Python :: 3.5
Classifier: Programming Language :: Python :: 3.6
